{
  "inputs": {
    "clusters": "clusters.tsv",
    "motif_hits": "motif_features.tsv"
  },
  "kind": "motif_cluster_scoreboard_meta",
  "output": "motif_cluster_scoreboard.pkl",
  "schema_version": "1.0",
  "stats": {
    "accessions_in_clusters": 495286,
    "calibration": [
      {
        "avg_predictions": 104.32073507259585,
        "coverage": 0.6387848379669404,
        "covered_accessions": 315996,
        "eligible_accessions": 494683,
        "set_accuracy": 0.7625792731553565,
        "set_correct_accessions": 240972,
        "top1_accuracy": 0.4541956227294016,
        "top1_correct_accessions": 143524,
        "top3_accuracy": 0.5734344738540994,
        "top3_correct_accessions": 181203,
        "weight_threshold": 2.0
      },
      {
        "avg_predictions": 59.70851213306498,
        "coverage": 0.6387848379669404,
        "covered_accessions": 315996,
        "eligible_accessions": 494683,
        "set_accuracy": 0.7363036240965075,
        "set_correct_accessions": 232669,
        "top1_accuracy": 0.4541956227294016,
        "top1_correct_accessions": 143524,
        "top3_accuracy": 0.5729154799427841,
        "top3_correct_accessions": 181039,
        "weight_threshold": 2.5
      },
      {
        "avg_predictions": 37.926701434546494,
        "coverage": 0.5442151842695221,
        "covered_accessions": 269214,
        "eligible_accessions": 494683,
        "set_accuracy": 0.8334447688456024,
        "set_correct_accessions": 224375,
        "top1_accuracy": 0.5331186342463616,
        "top1_correct_accessions": 143523,
        "top3_accuracy": 0.6707377773815626,
        "top3_correct_accessions": 180572,
        "weight_threshold": 3.0
      },
      {
        "avg_predictions": 11.493514453185941,
        "coverage": 0.5442151842695221,
        "covered_accessions": 269214,
        "eligible_accessions": 494683,
        "set_accuracy": 0.780122876224862,
        "set_correct_accessions": 210020,
        "top1_accuracy": 0.5331186342463616,
        "top1_correct_accessions": 143523,
        "top3_accuracy": 0.6679518895748364,
        "top3_correct_accessions": 179822,
        "weight_threshold": 3.5
      },
      {
        "avg_predictions": 7.723358222515202,
        "coverage": 0.4783851476602188,
        "covered_accessions": 236649,
        "eligible_accessions": 494683,
        "set_accuracy": 0.8782542922218137,
        "set_correct_accessions": 207838,
        "top1_accuracy": 0.6057283149305511,
        "top1_correct_accessions": 143345,
        "top3_accuracy": 0.7585538075377458,
        "top3_correct_accessions": 179511,
        "weight_threshold": 4.0
      },
      {
        "avg_predictions": 6.035178682352345,
        "coverage": 0.4783851476602188,
        "covered_accessions": 236649,
        "eligible_accessions": 494683,
        "set_accuracy": 0.8714213877937367,
        "set_correct_accessions": 206221,
        "top1_accuracy": 0.6057283149305511,
        "top1_correct_accessions": 143345,
        "top3_accuracy": 0.756846637847614,
        "top3_correct_accessions": 179107,
        "weight_threshold": 4.5
      },
      {
        "avg_predictions": 5.570822281167109,
        "coverage": 0.4534520086600914,
        "covered_accessions": 224315,
        "eligible_accessions": 494683,
        "set_accuracy": 0.9118962173728908,
        "set_correct_accessions": 204552,
        "top1_accuracy": 0.6390343935982882,
        "top1_correct_accessions": 143345,
        "top3_accuracy": 0.7978334039185966,
        "top3_correct_accessions": 178966,
        "weight_threshold": 5.0
      },
      {
        "avg_predictions": 5.042206755635017,
        "coverage": 0.44322121439386436,
        "covered_accessions": 219254,
        "eligible_accessions": 494683,
        "set_accuracy": 0.9252602004980525,
        "set_correct_accessions": 202867,
        "top1_accuracy": 0.6537851076833262,
        "top1_correct_accessions": 143345,
        "top3_accuracy": 0.8135222162423491,
        "top3_correct_accessions": 178368,
        "weight_threshold": 5.5
      },
      {
        "avg_predictions": 4.668635463891195,
        "coverage": 0.44322121439386436,
        "covered_accessions": 219254,
        "eligible_accessions": 494683,
        "set_accuracy": 0.9158647048628531,
        "set_correct_accessions": 200807,
        "top1_accuracy": 0.6537851076833262,
        "top1_correct_accessions": 143345,
        "top3_accuracy": 0.812126574657703,
        "top3_correct_accessions": 178062,
        "weight_threshold": 6.0
      },
      {
        "avg_predictions": 4.170154250321545,
        "coverage": 0.44322121439386436,
        "covered_accessions": 219254,
        "eligible_accessions": 494683,
        "set_accuracy": 0.8975298056135806,
        "set_correct_accessions": 196787,
        "top1_accuracy": 0.6537851076833262,
        "top1_correct_accessions": 143345,
        "top3_accuracy": 0.8072144635901739,
        "top3_correct_accessions": 176985,
        "weight_threshold": 6.5
      },
      {
        "avg_predictions": 3.3194297683726237,
        "coverage": 0.43235364870027876,
        "covered_accessions": 213878,
        "eligible_accessions": 494683,
        "set_accuracy": 0.8755739253219125,
        "set_correct_accessions": 187266,
        "top1_accuracy": 0.6632519473718662,
        "top1_correct_accessions": 141855,
        "top3_accuracy": 0.8109669998784353,
        "top3_correct_accessions": 173448,
        "weight_threshold": 7.0
      },
      {
        "avg_predictions": 2.7254819355869664,
        "coverage": 0.4174612832864683,
        "covered_accessions": 206511,
        "eligible_accessions": 494683,
        "set_accuracy": 0.8473592205742067,
        "set_correct_accessions": 174989,
        "top1_accuracy": 0.6751068950322259,
        "top1_correct_accessions": 139417,
        "top3_accuracy": 0.8055260978834057,
        "top3_correct_accessions": 166350,
        "weight_threshold": 7.5
      },
      {
        "avg_predictions": 2.3661454153226424,
        "coverage": 0.3954431423760267,
        "covered_accessions": 195619,
        "eligible_accessions": 494683,
        "set_accuracy": 0.8572173459633267,
        "set_correct_accessions": 167688,
        "top1_accuracy": 0.7013735884551092,
        "top1_correct_accessions": 137202,
        "top3_accuracy": 0.825436179512215,
        "top3_correct_accessions": 161471,
        "weight_threshold": 8.0
      }
    ],
    "clusters": 2849,
    "clusters_below_min_size": 135,
    "duplicate_motif_hits": 0,
    "eligible_clusters": 2714,
    "ignored_background_unavailable": 0,
    "ignored_cluster_size": 174285,
    "ignored_low_support": 3478749,
    "ignored_non_positive_weight": 6993,
    "min_cluster_size": 10,
    "min_support": 5,
    "motif_hit_rows": 2521820,
    "motif_hits_outside_clusters": 0,
    "motifs": 1291,
    "potential_motif_cluster_combos": 3678059,
    "stored_weights": 18032,
    "total_nonzero_weights": 18032
  }
}